README.rst
frmt.py
setup.cfg
setup.py
frmt.egg-info/PKG-INFO
frmt.egg-info/SOURCES.txt
frmt.egg-info/dependency_links.txt
frmt.egg-info/requires.txt
frmt.egg-info/top_level.txt