Metadata-Version: 1.1
Name: frmt
Version: 2.0.0
Summary: Lightweight formatting (pretty-printing) of tables and times in Python
Home-page: https://github.com/sigvaldm/frmt.git
Author: Sigvald Marholm
Author-email: marholm@marebakken.com
License: LGPL
Platform: UNKNOWN
Classifier: Programming Language :: Python :: 2.7
Classifier: Programming Language :: Python :: 3.4
Classifier: Programming Language :: Python :: 3.5
Classifier: Programming Language :: Python :: 3.6
Classifier: Programming Language :: Python :: 3.7
